README.md
setup.cfg
setup.py
pyvpn/__init__.py
pyvpn/pyvpn.py
pyvpn.egg-info/PKG-INFO
pyvpn.egg-info/SOURCES.txt
pyvpn.egg-info/dependency_links.txt
pyvpn.egg-info/requires.txt
pyvpn.egg-info/top_level.txt
pyvpn/source/__init__.py
pyvpn/source/client.py
pyvpn/source/crypt.py
pyvpn/source/providers.py
pyvpn/source/routes.py
pyvpn/source/vpn.py