Metadata-Version: 2.1
Name: pyvpn
Version: 1.2
Summary: UNKNOWN
Home-page: https://github.com/vaibhavjaiman/PyVpn
Author: Vaibhav Jaiman
Author-email: vaibhavjaiman@gmail.com
License: GNU General Public License v3.0
Platform: UNKNOWN
Classifier: Programming Language :: Python :: 3.8
Classifier: Intended Audience :: Information Technology
Classifier: License :: OSI Approved :: Apache Software License
Classifier: Operating System :: OS Independent
